yandex_direct_api_wrapper/__init__.py
yandex_direct_api_wrapper/client.py
yandex_direct_api_wrapper/constants.py
yandex_direct_api_wrapper/exceptions.py
yandex_direct_api_wrapper-0.1.2.dist-info/METADATA
yandex_direct_api_wrapper-0.1.2.dist-info/WHEEL
yandex_direct_api_wrapper-0.1.2.dist-info/RECORD
